{
  "users": [
    {
      "id": "",
      "userName": "",
      "userProfileImgUrl": "",
      "userEmail": "",
      "userPassword": ""
    }
  ],
  "questions": [
    {
      "id": "",
      "title": "",
      "description": "",
      "ownerId": "",
      "likedBy": [],
      "dislikedBy": [],
      "isEdited": "",
      "editTimeStamp": "",
      "postTimeStamp": ""
    }
  ],
  "answers": [
    {
      "id": "",
      "description": "",
      "ownerId": "",
      "questionId": "",
      "likedBy": [],
      "dislikedBy": [],
      "isEdited": "",
      "editTimeStamp": "",
      "postTimeStamp": ""
    }
  ]
}
